{
    "fetch_time": "2026-03-09 12:50:08",
    "total_matches": 11,
    "best_parlay": {
        "combo": "周一005 + 周一006",
        "combined_odds": 5.35,
        "confidence": 76.0
    },
    "matches": [
        {
            "home_team": "西汉姆联",
            "away_team": "布伦特",
            "league": "英足总杯",
            "match_num": "周一003",
            "sp_home": 3.15,
            "sp_draw": 3.45,
            "sp_away": 1.92,
            "odds_movement": "主胜升水，客胜降水",
            "handicap_info": "让1",
            "intelligence": {
                "h_inj": "卢卡斯·法比安斯基 受伤 后背受伤 巴勃罗·费利佩·佩雷拉·德·耶稣 受伤 小腿受伤 ",
                "g_inj": "维塔利·贾内特 受伤 足部受伤 莱斯·尼尔森 小腿受伤 安东尼·米兰博 受伤 膝关节受伤 艾伦·希基 受伤 受伤 乔希·达席尔瓦 受伤 膝关节受伤 法比奥·卡瓦略 受伤 膝关节受伤 里科·亨利 受伤 肌肉挫伤 ",
                "h_bad": "1.从历史交锋记录来看，西汉姆联在面对布伦特福德时处于明显下风。双方近6次交手，西汉姆联仅取得1胜1平4负，进7球失11球，攻防两端均被对手压制。更令人担忧的是，西汉姆联已连续2场输给布伦特福德，面对这个对手时显得办法不多，心理层面难免处于劣势。 ",
                "g_bad": "1.布伦特福德本赛季近10个客场比赛，在落后的情况下最终客场输球率达100%。 2.布伦特福德轮换中场卡瓦略、轮换边锋尼尔森和替补中场米拉姆博均由于伤病问题，本场比赛缺席。 ",
                "match_points": "西汉姆联本赛季在英足总杯赛场上表现可圈可点，一路过关斩将闯入1/8决赛，彰显出一定的杯赛竞争力。回顾球队近10场各项赛事，取得4胜4平2负的成绩，整体发挥较为平稳，场均进球1.4个，场均失球1.2个，攻防两端的表现相对均衡。近期状态上，西汉姆联刚刚在客场1 - 0战胜富勒姆，球队士气得到一定提升，不过此前面对利物浦和切尔西等强队时，防线承受了较大压力，最终输掉了比赛。主场作战方面，西汉姆联近4场主场比赛仅收获1胜3平，主场优势未能充分展现。阵容方面，主力门将赫尔曼森、后卫万 - 比萨卡、托迪博、迪萨西、E.迪乌夫，中场绍切克、M.费尔南德斯，以及前锋鲍文、萨默维尔、卡斯特拉诺斯、威尔逊等球员均保持健康状态，但卢卡斯·法比安斯基（后背受伤）和巴勃罗·费利佩·佩雷拉·德·耶稣（小腿受伤）两名球员因伤缺阵，对球队阵容产生了一定影响。战术层面，西汉姆联主要采用4 - 2 - 4阵型，注重边路推进和前场压制，不过中场厚度稍显不足，面对布伦特福德时需加强防守强度。\n\n布伦特福德本赛季同样有着不错的表现，近10场比赛取得5胜2平3负的战绩，场均进球1.2个，场均失球1.2个，攻防数据与西汉姆联相近。近期状态良好，刚刚在客场与伯恩茅斯握手言和，此前在客场更是表现亮眼，4 - 3击败伯恩利、3 - 2力克纽卡斯尔、1 - 0战胜维拉，近7场客场比赛取得5胜1平1负的佳绩，具备较强的客场作战能力。阵容方面，主力门将凯莱赫、后卫卡约德、范登贝赫、柯林斯、亨利，中场亨德森、延森、达姆斯高，以及前锋瓦塔拉、沙德、蒂亚戈等球员均可出战，但球队伤病问题较为严重，法比奥·卡瓦略、安东尼·米兰博、乔希·达席尔瓦（膝关节受伤）、艾伦·希基、维塔利·贾内特、莱斯·尼尔森、里科·亨利等7名球员因伤缺阵，对球队阵容深度造成了一定影响。战术上，布伦特福德以4 - 3 - 3阵型为主，强调中场控制和快速反击，客场战术执行能力较强。\n\n综合分析：本场英足总杯1/8决赛，双方都具备一定的晋级实力。西汉姆联主场作战，阵容相对完整，但近期主场胜率不高，攻防两端表现平稳，杯赛经验丰富。布伦特福德则客场战绩优异，虽然伤病较多，但主力阵容依然具备较强战斗力，球队整体状态略优于主队。历史交锋方面，双方近一年仅有一次交手，布伦特福德2-0取胜，心理上稍占优势。综合来看，布伦特福德客场表现更佳，阵容虽有伤病但战术执行力强，西汉姆联需依靠主场和杯赛经验争取晋级。预计比赛节奏较快，双方防守端压力较大，布伦特福德有望凭借客场优势和反击能力取得晋级机会。\n\n推荐：负"
            },
            "expert_intro": "西汉姆联最近10次对阵布伦特输了7场，并且球队英超保组任务更为艰巨，实在无法抽身多线作战，西汉姆联今仗只能举手投降。",
            "base_face": "本场双方都是英超的球队。主队29轮积28分，排在第18位，状态不佳。客队29轮积44分，排在第7位。\n西汉姆联各项赛事近6场2胜3平1负，状态不错。布伦特各项赛事近6场3胜2平1负，状态不错。\n综合来看，客队优势较大。\n双方近6次交锋，西汉姆联取得1胜1平4负，处于下风。\n本场半全场分析\n胜负关系不明显，半全场不推荐\n主队近6场主场的上半场:\n领先4，打平2，落后0/4场有进球，1场有失球\n客队近6场客场的上半场:\n落后1，打平2，领先3/3场有失球，3场有进球",
            "home_rank": 0,
            "away_rank": 0,
            "home_id": 0,
            "away_id": 0,
            "id": 1,
            "date": "2026-03-09",
            "home_stats": {
                "played": 22,
                "wins": 5,
                "draws": 4,
                "losses": 13,
                "goals_for": 18,
                "goals_against": 23,
                "avg_goals_for": "0.84",
                "avg_goals_against": "1.08",
                "clean_sheets": 5,
                "form": "WLLLL",
                "rank": 13
            },
            "away_stats": {
                "played": 25,
                "wins": 7,
                "draws": 6,
                "losses": 12,
                "goals_for": 23,
                "goals_against": 24,
                "avg_goals_for": "0.94",
                "avg_goals_against": "0.99",
                "clean_sheets": 6,
                "form": "LLLDW",
                "rank": 12
            },
            "h2h": [],
            "prediction": {
                "predicted_score": "0-0",
                "home_win_pct": 34.0,
                "draw_pct": 36.2,
                "away_win_pct": 29.8,
                "confidence": 51,
                "result": "平局",
                "over_under_2_5": "小",
                "both_score": "否",
                "risk_level": "中",
                "gpt_analysis": "综合信息后，我的独立裁决偏向平局。理由如下：1）基本面上，西汉姆联排名更差，但近6场2胜3平1负，实际状态并不弱；布伦特福德近6场3胜2平1负，同样稳定，客队纸面优势存在但没有形成绝对压制。2）交锋层面，西汉姆联近年对布伦特福德明显吃亏，这对主队心理面不利，也是市场倾向客队的重要原因。3）伤停方面，西汉姆联伤病相对较少，主要是法比安斯基等个别缺席；布伦特福德伤停名单更长，涉及后场与轮换深度，客队阵容完整性反而不如主队，这会削弱其客场赢球把握。4）盘口水位显示主胜升水、客胜降水，市场资金明显更偏向客队，但模型胜率给出主34.6%、平36.2%、客29.2%，反而是平局概率最高，且客胜并未得到数据模型支持，说明盘口走势与模型判断存在背离，需防市场诱导。5）半场数据看，西汉姆联主场上半场稳定性不错，而布伦特福德客场上半场有一定进球能力，比赛更像是拉锯战。综合判断，本场客队不败概率不低，但直接打穿或稳胜依据不足，最合理结果是1比1平局。",
                "gemini_analysis": "未响应",
                "gpt_score": "西汉姆联 1-1 布伦特福德",
                "gemini_score": "?",
                "value_bets_summary": [
                    "主胜 EV+8.99%"
                ]
            },
            "is_recommended": false
        },
        {
            "home_team": "拉齐奥",
            "away_team": "萨索洛",
            "league": "意甲",
            "match_num": "周一004",
            "sp_home": 2.13,
            "sp_draw": 2.85,
            "sp_away": 3.24,
            "odds_movement": "主胜升水，客胜降水",
            "handicap_info": "让-1",
            "intelligence": {
                "h_inj": "萨穆尔·吉戈 受伤 踝关节扭伤 尼古拉·罗维拉 受伤 受伤 托马·巴希奇 受伤 伊万·普罗维德尔 受伤 肩部受伤 ",
                "g_inj": "爱德华多·皮尔拉诺罗 受伤 膝关节受伤 丹尼尔·波洛卡 受伤 肌肉挫伤 安德烈亚·皮纳蒙蒂 停赛 红牌停赛 法利·坎德 受伤 膝关节受伤 阿利乌·法德拉 受伤 受伤 ",
                "h_bad": "1.拉齐奥本赛季联赛27场比赛，得失球不超过2球的场次占联赛总场次的74%。 2.拉齐奥本赛季联赛27场比赛，在落后的情况下最终输球的场次占总负场的100%。 3.本赛季联赛拉齐奥27场比赛，得到7张红牌，是联赛得到红牌数最多的球队。 4.拉齐奥近期状态持续低迷，上场意大利杯主场2-2战平亚特兰大，近6场正式比赛未尝胜绩，仅取得4平2负的惨淡战绩。球队攻防两端缺乏稳定性，关键时刻屡屡错失良机，士气受挫，整体表现令人担忧。 5.拉齐奥在4天前刚刚经历了一场意大利杯的鏖战，体能消耗较大，恢复时间有限，整体储备明显处于劣势。本场联赛面对以逸待劳、近期状态火热的萨索洛，蓝鹰在体能层面将面临严峻考验，这或将成为影响比赛走势的关键因素。 6.拉齐奥主力中场巴什奇大腿受伤，本场比赛出战成疑。轮换中场罗维拉锁骨骨折，将缺席至5月初。后防老将吉戈踝关节受伤，将继续缺席。此外主力门将普罗维德尔肩部受伤，赛季报销。本赛季普罗维德尔联赛出场27次，贡献了12场零封。他的缺席对球队后防线影响巨大。 7.拉齐奥近期进攻端表现乏力，近10场正式比赛仅打入9球，场均进球不足1球，火力明显不足。其中多达5场比赛颗粒无收，锋线缺乏稳定得分点，进攻组织也显得单调低效。在面对密集防守时往往难以破局。 ",
                "g_bad": "1.萨索洛本赛季近10个客场比赛，在落后的情况下最终客场输球率达100%。 2.萨索洛在近6次联赛对阵拉齐奥的交锋中仅取得1胜1平4负，处于明显下风。期间全队仅攻入3球，却失掉9球，攻防两端均被对手全面压制，心理层面亦处劣势。 3.萨索洛轮换边锋法德拉因伤，将缺席至4月初。中场波洛卡半月板受伤，将继续伤缺。轮换后卫坎德膝关节损伤，赛季报销。此外，主力前锋皮纳蒙蒂上轮联赛得到红牌，本场比赛将被停赛。皮纳蒙蒂本赛季联赛出场26次其中25场首发，打入6球并送出3记助攻。他的停赛对球队进攻能力影响巨大。 ",
                "match_points": "拉齐奥本赛季在意甲联赛中表现平平，当前位列第11位，积34分，与欧战区和降级区均保持着一段距离，球队的主要目标是争取提升排名。近10场比赛，拉齐奥仅收获2胜5平3负的战绩，场均进球0.9个，场均失球1.4个，攻防两端的表现均不尽如人意。近期状态上，拉齐奥在主场与亚特兰大战成2-2平，而此前客场则以0-2不敌都灵，整体走势偏弱，且主场近4场比赛仅取得1胜1平2负，主场优势并不突出。阵容方面，主力门将普罗维德尔、后卫塔瓦雷斯、罗马尼奥利、吉拉，中场马鲁西奇、泰勒、卡塔尔迪、巴希鲁、马尔蒂尼，以及前锋扎卡尼、伊萨克森等球员均可出战，但萨穆尔·吉戈（踝关节扭伤）、托马·巴希奇、尼古拉·罗维拉三人因伤缺阵，对球队阵容深度造成了一定影响。战术上，拉齐奥主要采用3-5-2阵型，注重中场厚度和边路推进，但进攻端缺乏高效的终结能力，防守端也存在漏洞。\n\n萨索洛本赛季的表现略好于拉齐奥，目前排名第9，积38分，仍有机会冲击欧战区。近10场比赛，萨索洛取得5胜1平4负的成绩，场均进球1.2个，场均失球1.5个，攻防数据相较于拉齐奥略占优势。近期状态良好，萨索洛刚刚在主场以2-1战胜亚特兰大，此前还主场3-0大胜维罗纳、客场2-1力克乌迪内斯，整体走势向好。客场方面，萨索洛近4场取得2胜2负，表现尚可。阵容方面，主力门将A.穆里奇、后卫加西亚、伊泽斯、W.库利巴利，中场索斯特维德、马蒂奇、科内，以及前锋劳利恩特、皮纳蒙蒂、贝拉尔迪等球员均可出战，但爱德华多·皮尔拉诺罗、法利·坎德（膝关节受伤）、丹尼尔·波洛卡（肌肉挫伤）、安德烈亚·皮纳蒙蒂（红牌停赛）、内马尼亚·马蒂奇（累计黄牌停赛）、阿利乌·法德拉（受伤）六人因伤缺阵或停赛，对球队阵容深度产生了一定影响。战术上，萨索洛注重攻守平衡，强调前场冲击和中场组织，进攻端效率较高，但防守端失球较多。\n\n综合分析：双方积分排名中游，战意主要在于争取欧战资格和更高排名。拉齐奥近期状态偏弱，进攻端乏力，防守端漏洞较多，主场优势有限，且有三人伤缺。萨索洛则状态向好，近三场取得两胜一负，进攻端效率提升，但防守端失球较多，阵容伤病和停赛较为严重。历史交锋方面，近一年萨索洛1-0取胜，心理上稍占优势。综合来看，萨索洛状态更佳但伤病严重，拉齐奥主场作战但进攻端缺乏亮点，预计比赛节奏较快，双方防守端压力较大，拉齐奥有望凭借主场和阵容完整性取得微弱优势，此役看好拉齐奥主场拿下小胜。\n\n推荐：胜"
            },
            "expert_intro": "萨索洛近期表现令人惊喜，过去6轮联赛斩获5胜1负，目前更是处于三连胜中，状态火热的萨索洛此役定能攻陷已4轮不胜的拉齐奥。",
            "base_face": "本场为意甲第28轮的比赛。目前主队积34分，排在第11位。客队积38分，排在第9位。\n主队近6轮联赛1胜3平2负，状态一般;近5个主场1胜1平3负，主场状态较差。客队近6轮联赛5胜1负，状态上佳;近5个客场2胜1平2负，客场状态一般。\n综合来看，客队优势较大。\n双方近6次交锋，拉齐奥取得4胜1平1负，占据上风;在拉齐奥的主场，近3次交锋，拉齐奥取得2胜1平，占据绝对上风。\n本场半全场分析\n双方上半场打平的可能性为59%\n主队近6场联赛主场的上半场:\n领先0，打平3，落后3/0场有进球，3场有失球\n客队近6场联赛客场的上半场:\n落后2，打平3，领先1/3场有失球，2场有进球",
            "home_rank": 0,
            "away_rank": 0,
            "home_id": 0,
            "away_id": 0,
            "id": 2,
            "date": "2026-03-09",
            "home_stats": {
                "played": 23,
                "wins": 5,
                "draws": 4,
                "losses": 14,
                "goals_for": 16,
                "goals_against": 26,
                "avg_goals_for": "0.73",
                "avg_goals_against": "1.17",
                "clean_sheets": 5,
                "form": "LWLLL",
                "rank": 14
            },
            "away_stats": {
                "played": 28,
                "wins": 6,
                "draws": 6,
                "losses": 16,
                "goals_for": 20,
                "goals_against": 32,
                "avg_goals_for": "0.73",
                "avg_goals_against": "1.17",
                "clean_sheets": 7,
                "form": "LDDLL",
                "rank": 14
            },
            "h2h": [],
            "prediction": {
                "predicted_score": "0-0",
                "home_win_pct": 34.7,
                "draw_pct": 39.3,
                "away_win_pct": 26.0,
                "confidence": 51,
                "result": "平局",
                "over_under_2_5": "小",
                "both_score": "否",
                "risk_level": "中",
                "gpt_analysis": "专家观点明显倾向萨索洛，但官方模型给出的主胜35.9%、平39.3%、客胜24.8%，实际并不支持客队必胜，反而平局为最高概率结果。盘口为拉齐奥让1球，这与积分、近期状态和模型胜率并不完全匹配，属于主队名气与交锋优势带来的深盘定位；目前又出现主胜升水、客胜降水，说明市场对主队穿盘信心下降，资金更防范客队不败。伤停方面，拉齐奥缺少普罗维德尔、罗维拉等人，中后场稳定性受损；但萨索洛这边皮纳蒙蒂停赛影响更直接，头号前场终结点缺席会削弱其连续赢球的进攻效率。结合双方近况，萨索洛状态更热，但拉齐奥历史交锋和主场面对该对手仍有压制力；再考虑半场平局概率高达59%，本场更像是拉锯战而非一边倒。综合伤停、盘口异动、模型概率与交锋背景，独立裁决为拉齐奥难胜且让1球方向不宜高看，首选平局，次选主队小胜，比分倾向1-1。",
                "gemini_analysis": "未响应",
                "gpt_score": "拉齐奥 1-1 萨索洛",
                "gemini_score": "?",
                "value_bets_summary": []
            },
            "is_recommended": false
        },
        {
            "home_team": "敦刻尔克",
            "away_team": "兰斯",
            "league": "法乙",
            "match_num": "周一005",
            "sp_home": 3.28,
            "sp_draw": 2.95,
            "sp_away": 2.06,
            "odds_movement": "主胜升水，客胜降水",
            "handicap_info": "让1",
            "intelligence": {
                "h_inj": "塞娜·马索克 停赛 轮休 阿里斯蒂德·佐苏 受伤 埃迪·西尔维斯特 停赛 轮休 伊尼哥·埃瓜拉斯 停赛 轮休 阿贝内·费利佩 停赛 轮休 文森特·萨索 停赛 轮休 马尔科·艾西米 停赛 轮休 ",
                "g_inj": "约瑟夫·奥库木 受伤 膝关节受伤 哈菲兹·奥马尔·易卜拉欣 停赛 轮休 ",
                "h_bad": "1.敦刻尔克在上场联赛中客场1比2不敌克莱蒙，球队在近6场联赛中仅取得1胜2平3负的战绩，整体表现难言理想。此外他们的主场状态也存在明显起伏，近3个联赛主场录得2平1负，至今未能品尝到胜利的滋味。 2.敦刻尔克的进攻能力显得相当有限，球队在近6场联赛中总共只打进6球，场均进球数仅为1个，期间更有3场比赛未能取得任何进球，进攻端的稳定性严重不足。 3.敦刻尔克近期竞技状态出现明显下滑，即便在赛程强度不高且连续面对中下游球队的情况下依然表现不佳，取分势头显著放缓。反观兰斯虽然近期陷入平局怪圈，但防守端始终保持极其稳健的态势，整条防线固若金汤。考虑到敦刻尔克目前缺乏足以攻破对方严密防线的进攻手段，他们本场想要在主场击败对手恐怕难度极大。 4.敦刻尔克目前正遭受严重的伤病困扰，多名关键球员无法登场。后防核心萨索依旧未能复出，他本赛季在19场联赛中全部首发出战，其缺阵影响巨大。此外，主力后卫阿贝内、中场大将埃瓜拉斯与西尔维斯特、边路好手艾西米以及中场球员马索克等人也均处于缺阵状态，球队阵容深度受到严峻考验。 ",
                "g_bad": "1.兰斯在上场法国杯赛事中客场1比2不敌斯特拉斯堡，球队在近5场正式比赛中交出4平1负的答卷，始终未能收获胜利，整体状态显得十分平庸。此外他们在客场的竞争力也较为有限，近5个正式比赛客场仅取得1胜2平2负，胜率低至20%，难以在对手主场占据主动。 ",
                "match_points": "敦刻尔克目前在法乙联赛排名第8位，积分38分，处于中游位置，球队近三场比赛表现起伏较大，分别是客场1比2负于克莱蒙、主场1比1战平巴斯蒂亚、客场4比1大胜亚眠，整体来看，敦刻尔克在进攻端有一定爆发力，尤其是客场对亚眠的胜利展现了球队的反击能力，但防守端偶有漏洞，近三场丢了4球。主场表现相对稳定，近期能保持不败，但胜率并不高。\n\n兰斯目前排名第4，积分42分，处于升级附加赛区，战意较强。兰斯近三场比赛分别是客场1比2负于斯特拉斯、客场0比0战平蒙彼利埃、主场0比0战平亚眠。兰斯近期防守能力突出，连续两场零封对手，但进攻端陷入低迷，三场只打入1球。球队客场表现尚可，但整体攻坚能力不足，近期平局较多，缺乏取胜的关键突破。\n\n综合分析，两队排名接近但兰斯略占优势，且有升级附加赛压力，敦刻尔克近期状态波动，主场有一定稳定性但攻防平衡不足，兰斯防守稳健但进攻乏力，平局概率较高，考虑到双方近况和排名，看好客场兰斯取胜。\n\n推荐：负"
            },
            "expert_intro": "敦刻尔克此前3场法乙主场不胜，期间战绩为2和1负，而兰斯在联赛连续遭遇和局，双方此番对决和味浓。",
            "base_face": "本场为法乙第26轮的比赛。目前主队积38分，排在第7位。客队积42分，排在第4位。\n主队近6轮联赛1胜2平3负，状态一般;近5个主场2胜2平1负，主场状态不错。客队近6轮联赛2胜4平，状态不错;近5个客场1胜3平1负，客场状态一般。\n综合来看，客队稍占优势。\n双方近几年双方只交锋过一次，USL敦刻尔克获胜。\n本场半全场分析\n双方上半场打平的可能性为64%\n主队近6场联赛主场的上半场:\n领先1，打平4，落后1/2场有进球，2场有失球\n客队近6场联赛客场的上半场:\n落后1，打平4，领先1/2场有失球，1场有进球",
            "home_rank": 0,
            "away_rank": 0,
            "home_id": 0,
            "away_id": 0,
            "id": 3,
            "date": "2026-03-09",
            "home_stats": {
                "played": 24,
                "wins": 10,
                "draws": 6,
                "losses": 8,
                "goals_for": 32,
                "goals_against": 15,
                "avg_goals_for": "1.37",
                "avg_goals_against": "0.63",
                "clean_sheets": 6,
                "form": "DWDDL",
                "rank": 8
            },
            "away_stats": {
                "played": 27,
                "wins": 7,
                "draws": 5,
                "losses": 15,
                "goals_for": 22,
                "goals_against": 29,
                "avg_goals_for": "0.84",
                "avg_goals_against": "1.08",
                "clean_sheets": 6,
                "form": "WWLDD",
                "rank": 13
            },
            "h2h": [],
            "prediction": {
                "predicted_score": "1-0",
                "home_win_pct": 42.8,
                "draw_pct": 29.4,
                "away_win_pct": 27.8,
                "confidence": 76,
                "result": "主胜",
                "over_under_2_5": "小",
                "both_score": "否",
                "risk_level": "低",
                "gpt_analysis": "基础面上，敦刻尔克排名第7、兰斯第4，客队整体积分与近6轮稳定性更好。敦刻尔克近6轮仅1胜，虽然近5个主场2胜2平1负不差，但主队伤停过多，包含多名停赛轮休与伤员，对阵容完整度和临场调整影响明显；兰斯仅2名减员，伤停压力明显更小。盘口与水位层面，出现主胜升水、客胜降水，说明市场资金更偏向客队不败甚至客胜，与官方“客队稍占优势”一致。与此同时，双方上半场打平概率高，且两队近期平局属性都较强，比赛节奏大概率谨慎。综合伤停、市场倾向与平局特征，独立裁决倾向兰斯不败，比分首选1-1，激进方向可防0-1。",
                "gemini_analysis": "未响应",
                "gpt_score": "0-1",
                "gemini_score": "?",
                "value_bets_summary": [
                    "主胜 EV+62.03%"
                ]
            },
            "is_recommended": true
        },
        {
            "home_team": "西班牙人",
            "away_team": "奥维耶多",
            "league": "西甲",
            "match_num": "周一006",
            "sp_home": 1.63,
            "sp_draw": 3.35,
            "sp_away": 4.6,
            "odds_movement": "主胜降水，客胜升水",
            "handicap_info": "让-1",
            "intelligence": {
                "h_inj": "哈维·普阿多 受伤 膝关节受伤 查尔斯·皮克尔 停赛 红牌停赛 安东尼乌·罗卡 肩部受伤 埃杜·埃斯波西托 停赛 累计黄牌停赛 ",
                "g_inj": "卢卡斯·阿伊哈多 受伤 受伤 大卫·科斯塔斯 受伤 肌肉挫伤 利恩德·登东克尔 受伤 受伤 蒂亚戈·波巴斯 受伤 受伤 ",
                "h_bad": "1.西班牙人6场比赛2平4负，难求一胜。 2.西班牙人本赛季联赛26场比赛，在落后的情况下最终输球的场次占总负场的70%。 3.西班牙人在上一轮联赛客场与埃尔切2比2握手言和，球队在近9轮联赛中交出3平6负的糟糕答卷，至今未能品尝胜利滋味，整体状态陷入极度低迷。此外，他们的主场表现也出现显著下滑，近4个联赛主场仅取得1平3负的成绩，同样未尝胜绩，面临严峻挑战。 4.西班牙人在防守端的表现可谓糟糕透顶，球队已经连续10轮联赛被对手攻破球门，期间总计失守23球，场均丢球数高达2.3个。如此频繁的失球不仅暴露出防线效率的极度低下，更显示出整体防守体系缺乏必要的稳定性，难以在整场比赛中保持专注并抵挡住对手的持续冲击。 5.西班牙人在本场中场方面遭遇重创，两员大将因故停赛。球队中场核心埃斯波西托因累计黄牌数达到上限被罚停赛1场，本赛季他出战25场联赛并有21次首发，贡献1球和6次助攻，在攻防两端都扮演着极为关键的角色。另外主力轮换中场皮克尔在上轮比赛中吃到红牌，本场同样被罚停赛，他本赛季出战16场联赛仅有3次首发。此外，球队队长兼前锋普阿多目前仍长期缺席，阵容实力受到进一步削弱。 ",
                "g_bad": "1.本赛季联赛皇家奥维耶多客场3平9负，表现低迷。 2.皇家奥维耶多本赛季联赛26场进16球，是联赛进球数第1少的球队。 3.皇家奥维耶多本赛季联赛26场失43球，是联赛失球数第2多的球队。 4.皇家奥维耶多近5年面对西班牙人客场输球率达到66%。 5.皇家奥维耶多本赛季联赛26场比赛，在落后的情况下最终输球的场次占总负场的80%。 6.皇家奥维耶多本赛季近10个客场比赛，在落后的情况下最终客场输球率达71%。 7.本赛季联赛皇家奥维耶多26场比赛，得到8张红牌，是联赛得到红牌数最多的球队。 8.本赛季联赛26场比赛，维纳斯得到3张红牌，是联赛获得红牌最多的球员。 9.皇家奥维耶多在上一轮联赛客场0比3完败给巴列卡诺，球队在近4轮联赛中仅取得1平3负的惨淡战绩，至今未能收获胜利，整体状态陷入极度低迷。更令人担忧的是，他们在客场的竞争力极其低下，本赛季13个联赛客场仅取得1胜3平9负的成绩，尤其是近9个联赛客场更是交出3平6负的答卷，一胜难求，抢分能力着实令人堪忧。 10.皇家奥维耶多近期表现堪称攻防两端全面崩盘，球队在近6场联赛中仅仅打进5球，更有3场比赛未能取得进球，尤其是最近2轮比赛更是一球未进。防守端同样漏洞百出，这6场比赛共丢12球，场均丢球数高达2个，整体防守效率极其低下，难以抵挡对手的冲击。 11.皇家奥维耶多在本场比赛中面临多名主力球员伤缺的严峻局面，主力中场登东克尔因伤缺席，本赛季他代表球队出战19场联赛并贡献15次首发。此外，主力后卫阿伊哈多同样因伤缺阵，他本赛季出战15场联赛且有10次首发记录，轮换前锋波巴斯也继续因伤高挂免战牌，阵容完整性受到影响。 ",
                "match_points": "西班牙人目前在西甲联赛排名第7，积分36分，处于中上游。近三场比赛分别是客场2比2战平埃尔切、客场2比4负于马竞、主场2比2战平塞尔塔。球队近期状态一般，连续两场打出平局，进攻端表现尚可，但防守端问题突出，三场丢了8球。整体来看，西班牙人具备一定的进攻能力，但防守漏洞较大，主场表现也不够理想，近期胜率偏低。\n\n奥维耶多目前排名第20，积分17分，处于降级区，保级压力极大。近三场比赛分别是客场0比3负于巴列卡诺、主场0比1负于马竞、客场3比3战平皇家社会。奥维耶多近期状态低迷，连续两场失利，防守端同样不稳，三场丢了7球。球队进攻端偶有亮点，能在客场与皇家社会打出3比3，但整体实力与主队存在明显差距。\n\n综合分析，西班牙人排名和积分优势明显，近期虽防守不佳但进攻端有一定保障。奥维耶多则处于降级区，状态低迷，保级压力大。两队近况都不理想，但主队整体实力更强，且主场作战有一定优势，本场西班牙人取得胜利。\n\n推荐：胜"
            },
            "expert_intro": "西班牙人进入2026年以来9场联赛惨遭3和6负，这与赛季前半程简直判若两队，球队急需赢球重整旗鼓。幸好今轮遇上奥维耶多，联赛副班长实力不济并非秘密，今季首循环西班牙人曾作客两球完胜对方，何况奥维耶多本身联赛作客防守特别差(均场失2球以上)，西班牙人今铺称雄在即。",
            "base_face": "本场为西甲第27轮的比赛。目前主队积36分，排在第7位。客队只积17分，排在第20位。主队实力更强。\n主队近6轮联赛2平4负，状态低迷;近5个主场1胜1平3负，主场状态较差。客队近6轮联赛1胜1平4负，状态较差;近5个客场2平3负，客场状态低迷。\n综合来看，主队稍占优势。\n双方近5次交锋，西班牙人取得3胜2负，略占上风;在西班牙人的主场，近2次交锋，西班牙人取得全胜，占据绝对上风。\n本场半全场分析\n双方上半场打平的可能性为53%\n主队近6场联赛主场的上半场:\n领先1，打平3，落后2/2场有进球，3场有失球\n客队近6场联赛客场的上半场:\n落后2，打平4，领先0/3场有失球，1场有进球",
            "home_rank": 0,
            "away_rank": 0,
            "home_id": 0,
            "away_id": 0,
            "id": 4,
            "date": "2026-03-09",
            "home_stats": {
                "played": 25,
                "wins": 10,
                "draws": 6,
                "losses": 9,
                "goals_for": 34,
                "goals_against": 15,
                "avg_goals_for": "1.37",
                "avg_goals_against": "0.63",
                "clean_sheets": 6,
                "form": "DWWLD",
                "rank": 8
            },
            "away_stats": {
                "played": 23,
                "wins": 5,
                "draws": 4,
                "losses": 14,
                "goals_for": 19,
                "goals_against": 24,
                "avg_goals_for": "0.84",
                "avg_goals_against": "1.08",
                "clean_sheets": 5,
                "form": "WWWWL",
                "rank": 13
            },
            "h2h": [],
            "prediction": {
                "predicted_score": "1-0",
                "home_win_pct": 42.7,
                "draw_pct": 31.0,
                "away_win_pct": 26.3,
                "confidence": 76,
                "result": "主胜",
                "over_under_2_5": "小",
                "both_score": "否",
                "risk_level": "低",
                "gpt_analysis": "西班牙人纸面实力、交锋和主场对位都占优，且盘口维持主让1球并伴随主胜降水，市场对主队支持力度仍在。虽然西班牙人近期联赛连续不胜、状态明显下滑，而且前场的普阿多伤缺、皮克尔与埃斯波西托停赛，对进攻流畅性和轮换有一定影响，但奥维耶多本身排名垫底，客场防守失球率高，且同样存在多名伤员，整体抗压能力有限。结合半场平局概率较高、主队近期上半场进入状态偏慢，本场更像是西班牙人先稳后发力的比赛。独立裁决倾向主胜，赢球机会大于穿深盘机会，防范一球小胜，次选两球完胜。",
                "gemini_analysis": "未响应",
                "gpt_score": "2-0",
                "gemini_score": "?",
                "value_bets_summary": []
            },
            "is_recommended": true
        },
        {
            "home_team": "通德拉",
            "away_team": "里奥阿维",
            "league": "葡超",
            "match_num": "周一007",
            "sp_home": 2.0,
            "sp_draw": 3.06,
            "sp_away": 3.3,
            "odds_movement": "主胜平稳，客胜升水",
            "handicap_info": "让-1",
            "intelligence": {
                "h_inj": "",
                "g_inj": "",
                "h_bad": "1.通德拉本赛季在主场作战时的表现极其糟糕，球队在总共12个联赛主场中仅取得1胜5平6负的战绩，整体拿分能力令人深感担忧，主场比赛的竞争力严重不足。 ",
                "g_bad": "1.里奥阿维在上场联赛主场以0比0战平法马康利，球队在近7轮联赛中仅取得1平6负的惨淡战绩，始终一胜难求，整体状态极其低迷。此外，他们的客场表现同样较为糟糕，在近5个联赛客场中仅收获1平4负，至今未尝胜绩，客战能力令人担忧。 2.里奥阿维近期表现堪称攻防俱废，球队在近7轮联赛中仅打进1球，其中多达6场交出白卷，进攻端显得极度无能。防守端同样漏洞百出，7场比赛共丢15球，场均丢球高达2.14球，防守效率十分低下，且每场比赛都未能零封对手，整体稳定性令人深感担忧。 ",
                "match_points": "通德拉目前在葡超联赛排名第16，积分19分，处于降级附加赛区，保级压力较大。近三场比赛分别是主场2比2战平圣克拉拉、客场2比0战胜阿马多拉、主场1比1战平阿维卡。球队近期状态有所回升，连续三场保持不败，进攻端表现积极，三场打入5球，防守端也较为稳健。整体来看，通德拉主场战绩尚可，近期能稳定拿分，士气有所提升。\n\n里奥阿维目前排名第15，积分21分，略高于通德拉但同样处于下游。近三场比赛分别是主场0比0战平法马利康、客场0比1负于波尔图、主场1比2负于摩雷伦斯。球队近况低迷，三场未尝胜绩，进攻端乏力，仅打入1球，防守端压力较大。整体来看，里奥阿维客场表现不佳，近期状态下滑，攻防两端均需调整。\n\n综合分析，两队排名接近，均有保级压力。通德拉近期状态回升，主场作战有一定优势，进攻端表现更为活跃。里奥阿维则近况低迷，客场战绩较差，进攻端缺乏突破。本场比赛通德拉借主场之利取胜。\n\n推荐：胜"
            },
            "expert_intro": "里奥阿维联赛作客均场失2球，球队防守端形同虚设，反观通德拉近期联赛保持不败，此消彼长之下，通德拉此番值得看高一线。",
            "base_face": "本场为葡超第25轮的比赛。目前主队只积19分，排在第17位。客队积21分，排在第16位。双方本赛季表现都不理想。\n主队近6轮联赛1胜4平1负，近5个主场1胜3平1负，状态一般。客队近6轮联赛1平5负，近5个客场1平4负，状态低迷。\n综合来看，主队优势较大。\n双方近几年双方只交锋过一次，里奥阿维获胜。\n本场半全场分析\n主队上半场领先的可能性为43%\n主队近6场联赛主场的上半场:\n领先1，打平4，落后1/2场有进球，3场有失球\n客队近6场联赛客场的上半场:\n落后4，打平1，领先1/5场有失球，2场有进球",
            "home_rank": 0,
            "away_rank": 0,
            "home_id": 0,
            "away_id": 0,
            "id": 5,
            "date": "2026-03-09",
            "home_stats": {
                "played": 27,
                "wins": 8,
                "draws": 6,
                "losses": 13,
                "goals_for": 28,
                "goals_against": 24,
                "avg_goals_for": "1.05",
                "avg_goals_against": "0.9",
                "clean_sheets": 6,
                "form": "DLWDW",
                "rank": 11
            },
            "away_stats": {
                "played": 22,
                "wins": 8,
                "draws": 5,
                "losses": 9,
                "goals_for": 27,
                "goals_against": 15,
                "avg_goals_for": "1.26",
                "avg_goals_against": "0.72",
                "clean_sheets": 5,
                "form": "LWLLL",
                "rank": 9
            },
            "h2h": [],
            "prediction": {
                "predicted_score": "0-0",
                "home_win_pct": 34.7,
                "draw_pct": 31.4,
                "away_win_pct": 33.9,
                "confidence": 56,
                "result": "平局",
                "over_under_2_5": "小",
                "both_score": "否",
                "risk_level": "中",
                "gpt_analysis": "两队分列第17和第16，整体实力接近，模型胜率也仅是主队微弱占优。基本面上，通德拉近6轮1胜4平1负，稳定性略好于里奥阿维近6轮1平5负；里奥阿维客场均场失球偏高，防线问题明显。伤停信息两队均无明确利空，阵容层面没有额外打击。盘口给到主让-1，与双方积分和模型概率相比偏深，更像是借客队低迷与主队不败题材造强主队，实际支撑力度不足；同时主胜平稳、客胜升水，说明市场对客队反弹防范有限，但未形成主队明显穿盘的强信号。结合双方进攻效率都不高、保级战背景下谨慎属性较强，本场更看好通德拉不败，但主让-1下赢一球甚至被逼平的概率不低。",
                "gemini_analysis": "未响应",
                "gpt_score": "1-1",
                "gemini_score": "?",
                "value_bets_summary": []
            },
            "is_recommended": false
        },
        {
            "home_team": "印度女",
            "away_team": "中国台女",
            "league": "女亚洲杯",
            "match_num": "周二001",
            "sp_home": 7.5,
            "sp_draw": 4.0,
            "sp_away": 1.34,
            "odds_movement": "主胜平稳，客胜平稳",
            "handicap_info": "让1",
            "intelligence": {
                "h_inj": "",
                "g_inj": "",
                "h_bad": "1.印度女足在上一场小组赛第二轮中以0比11的悬殊比分惨败于日本女足脚下，遭遇了一场毁灭性的打击。本届女足亚洲杯两战皆墨，球队整体状态极度低迷。大比分失利让全队士气跌落谷底，球员们在场上显得信心全无。 2.印度女足在本届赛事中的表现堪称攻防两端全面崩盘，两场小组赛战罢仅打入1球，上场面对日本女足时更是颗粒无收，进攻端显得极度乏力。防守端的问题则更为严峻，两场比赛合计狂丢13球，防线仿佛形同虚设，尤其是上一轮对阵日本女足时单场就失守11球，如此糟糕的防守数据彻底暴露了球队整体实力的巨大差距与战术体系的严重缺失。 3.印度女足曾在2023年亚运会赛场上与中国台北女足有过直接对话，当时她们以1比2的比分遗憾落败。这段过往交锋记录很可能给印度女足将士带来不小的心理压力，毕竟面对同一对手时的失利记忆往往会影响球员在场上的自信心与战术执行力，使得她们在本场比赛中更加难以放开手脚去争取理想结果。 ",
                "g_bad": "1.中国台北女足在进攻端的火力显得较为有限，纵观本届赛事前两轮较量，全队总计仅打入1粒进球。此前面对实力超群的日本女足时，她们难以创造出具有实质威胁的进攻机会，而上轮对阵越南女足的比赛中，球队也仅仅依靠单球小胜，整体进攻效率与终结能力亟待提升。 ",
                "match_points": ""
            },
            "expert_intro": "印度女足前2场女亚杯遭遇全败打击，当中得失球为1比13，球队攻守发挥失衡，印度女足今仗打定输数。",
            "base_face": "在女亚杯C组中，主队目前2场积0分，排在第4名;客队目前2场积3分，排在第3名。\n主队各项赛事近6场3胜1平2负，状态一般;近5个主场1胜1平3负，主场状态较差。客队各项赛事近6场3胜3负，近5个客场2胜3负，状态一般。\n综合来看，双方差距不大。\n双方近几年双方只交锋过一次，中国台湾女足获胜。",
            "home_rank": 0,
            "away_rank": 0,
            "home_id": 0,
            "away_id": 0,
            "id": 6,
            "date": "2026-03-09",
            "home_stats": {
                "played": 23,
                "wins": 5,
                "draws": 5,
                "losses": 13,
                "goals_for": 16,
                "goals_against": 26,
                "avg_goals_for": "0.73",
                "avg_goals_against": "1.17",
                "clean_sheets": 5,
                "form": "WLWWL",
                "rank": 14
            },
            "away_stats": {
                "played": 23,
                "wins": 8,
                "draws": 5,
                "losses": 10,
                "goals_for": 26,
                "goals_against": 18,
                "avg_goals_for": "1.16",
                "avg_goals_against": "0.81",
                "clean_sheets": 5,
                "form": "DWDWW",
                "rank": 10
            },
            "h2h": [],
            "prediction": {
                "predicted_score": "0-0",
                "home_win_pct": 29.1,
                "draw_pct": 34.7,
                "away_win_pct": 36.2,
                "confidence": 66,
                "result": "平局",
                "over_under_2_5": "小",
                "both_score": "否",
                "risk_level": "中",
                "gpt_analysis": "伤停信息显示双方均无明确利空，阵容完整度对比赛影响有限。结合基本面，印度女足前两场亚洲杯全败且失13球，仅入1球，防线质量和比赛强度明显不足；中国台女虽然整体稳定性一般，但小组赛积分、过往交锋和整体对抗能力仍占优。盘口给到让1，说明市场对客队支持力度较明确，且水位平稳，未见明显降档，倾向中国台女至少赢一球。考虑模型胜率中客胜仅略高于平局，说明穿盘空间不算特别充足，但在印度女足防守持续失衡背景下，客队赢面依然更高。独立裁决倾向中国台女常规时间取胜，看好1球以上优势。",
                "gemini_analysis": "未响应",
                "gpt_score": "中国台女 -1 胜",
                "gemini_score": "?",
                "value_bets_summary": [
                    "主胜 EV+98.75%"
                ]
            },
            "is_recommended": false
        },
        {
            "home_team": "日本女",
            "away_team": "越南女",
            "league": "女亚洲杯",
            "match_num": "周二002",
            "sp_home": 0.0,
            "sp_draw": 0.0,
            "sp_away": 0.0,
            "odds_movement": "主胜平稳，客胜平稳",
            "handicap_info": "让-4",
            "intelligence": {
                "h_inj": "",
                "g_inj": "",
                "h_bad": "1.日本女足在前两场小组赛中均顺利取胜，此役面对实力有限的越南女足，只需保持不败便可锁定小组头名出线，并且本场球队可能有所松懈，战意有限。鉴于对手很难构成实质性威胁，日本队极有可能进行较大幅度的人员轮换，让核心球员获得宝贵的休整时间，从而为后续淘汰赛阶段储备更充沛的体能与竞技状态。 ",
                "g_bad": "1.越南女足近10场正赛4胜0平6负，状态低迷。 2.越南女足近5场正赛连续失球，且场均丢球达3.2球。 3.越南女足在上一场小组赛第二轮中以0比1惜败于中国台北女足，未能延续胜势。纵观本届赛事前两轮，她们取得1胜1负的战绩，其中唯一胜利是2比1小胜实力相对较弱的印度女足，这场胜利的含金量显得较为不足。整体竞争力仍有待进一步检验和提升。 4.越南女足在攻防两端的整体实力显得较为有限，虽然球队在首轮比赛中以2比1击败了印度女足，但需要看到对手本身的防守能力本就不足。上轮面对中国台北女足时她们未能取得进球，进攻端陷入停滞，而防守端更是两轮比赛都有失球记录。纵观各项赛事近5场较量，越南女足合计丢掉16球，如此频繁的失球充分暴露了球队防守效率低下的严峻问题，防线漏洞亟待解决。 5.越南女足在本届女足亚洲杯小组赛中仅击败过印度队，上轮不敌中国台北女足后出线形势已变得十分危急。此役她们寄希望于面对日本女足时尽可能减少失球，从而凭借成绩较好的小组第三身份争取出线资格。虽然球队战意高涨，但整体实力与日本女足存在巨大鸿沟，加之历史交锋层面遭到完全碾压，本场想要挑战强敌并拿分的前景依然极为渺茫。 ",
                "match_points": ""
            },
            "expert_intro": "日本女足前2场女亚杯全部获胜，并且球队过去3次面对越南女足也全部取胜，日本女足此番一定会乘胜追击。",
            "base_face": "在女亚杯C组中，主队目前2场积6分，排在第1名;客队目前2场积3分，排在第2名。\n日本女足各项赛事近6场4胜1平1负，状态上佳。越南女足各项赛事近6场1胜1平4负，状态较差。\n综合来看，双方差距不大。\n双方近2次交锋，日本女足取得全胜，占据绝对上风。",
            "home_rank": 0,
            "away_rank": 0,
            "home_id": 0,
            "away_id": 0,
            "id": 7,
            "date": "2026-03-09",
            "home_stats": {
                "played": 22,
                "wins": 5,
                "draws": 4,
                "losses": 13,
                "goals_for": 18,
                "goals_against": 23,
                "avg_goals_for": "0.84",
                "avg_goals_against": "1.08",
                "clean_sheets": 5,
                "form": "WLLLL",
                "rank": 13
            },
            "away_stats": {
                "played": 23,
                "wins": 5,
                "draws": 4,
                "losses": 14,
                "goals_for": 16,
                "goals_against": 26,
                "avg_goals_for": "0.73",
                "avg_goals_against": "1.17",
                "clean_sheets": 5,
                "form": "WLLLL",
                "rank": 14
            },
            "h2h": [],
            "prediction": {
                "predicted_score": "0-0",
                "home_win_pct": 35.6,
                "draw_pct": 38.7,
                "away_win_pct": 25.7,
                "confidence": 56,
                "result": "平局",
                "over_under_2_5": "小",
                "both_score": "否",
                "risk_level": "中",
                "gpt_analysis": "从基本面看，日本女足实力、排名、近期状态和历史交锋都明显占优，前2场全胜且攻防表现稳定；越南女足近况较差，硬实力与日本存在明显层级差。伤停信息显示双方暂无明确核心减员，主队可基本以完整阵容出战，这进一步放大日本女足的阵容深度优势。盘口方面主让-4，属于极深让步，说明外部预期不是简单胜负，而是日本女足有望取得大比分优势；且水位平稳，市场对主胜穿盘预期较一致。官方研报中“双方差距不大”与让-4盘口明显不符，参考价值偏低；模型给出的主胜概率也与实际基本面和盘口强度存在背离，因此本场更应重视实力面与盘口面的一致性。综合判断，日本女足大概率掌控比赛节奏，越南女足更多以防守应对，若日本早段破门，比分有继续拉开的可能。",
                "gemini_analysis": "未响应",
                "gpt_score": "5-0",
                "gemini_score": "?",
                "value_bets_summary": []
            },
            "is_recommended": false
        },
        {
            "home_team": "加拉塔萨",
            "away_team": "利物浦",
            "league": "欧冠",
            "match_num": "周二005",
            "sp_home": 3.98,
            "sp_draw": 3.9,
            "sp_away": 1.61,
            "odds_movement": "主胜平稳，客胜平稳",
            "handicap_info": "让1",
            "intelligence": {
                "h_inj": "格克代尼兹·古尔普兹 停赛 轮休 尤努斯·阿克昆 轮休 梅特汉·巴尔塔奇 停赛 停赛 阿尔达·尤尼亚 受伤 受伤 坎 停赛 轮休 雷纳托·纳加 停赛 轮休 巴特汉·阿赫米森 受伤 ",
                "g_inj": "乔瓦尼·莱奥尼 受伤 膝关节损伤 斯特凡·巴伊切蒂奇 受伤 腿筋受伤 亚历山大·伊萨克 受伤 腿部骨折 远藤航 受伤 受伤 里斯·威廉姆斯 停赛 轮休 康纳·布拉德利 受伤 膝关节损伤 哈维·戴维斯 停赛 轮休 ",
                "h_bad": "1.加拉塔萨雷在欧冠赛场的攻防两端表现均显局限，近6场赛事仅打入6球，其中多达5球来自附加赛首回合对阵尤文图斯，其余4场更是颗粒无收，虽偶有爆发但稳定性严重不足。防守端同样漏洞百出，6场比赛共失10球，场均失球达1.67个，且场场均有失球记录，尤其是最近3场场均失球数更高达2.33个，防线压力巨大。 2.加拉塔萨雷虽然素来拥有魔鬼主场的威名，并且此前在附加赛阶段曾在主场大胜尤文图斯，但本轮面对整体实力更为强劲的利物浦，情况则截然不同。利物浦的防线稳定性更强，而加拉塔萨雷自身在欧冠赛场的实际防守能力确实存在明显短板，且攻防两端表现缺乏足够的稳定性。鉴于这些因素，加拉塔萨雷本场很难复刻此前联赛阶段1比0力克利物浦的记录，此役他们坐镇主场想要击败强大的对手显得极为困难。 ",
                "g_bad": "1.利物浦近5年面对加拉塔萨雷客场输球率达到100%。 2.利物浦本赛季近10个客场比赛，在落后的情况下最终客场输球率达100%。 ",
                "match_points": ""
            },
            "expert_intro": "踏入2000年之后，利物浦欧战6次作客挑战土耳其对手，只得1胜1和4负，连同今届欧冠联联赛阶段在内，利物浦作客挑战加拉塔萨已经遭遇两连败，红军对此十分重视，他们在欧冠联联赛阶段发挥出色直接晋级，利物浦此行力争保住和局。",
            "base_face": "主队是土超的球队，目前在联赛中25轮积61分，排在第1位，状态火热。客队是英超的球队，目前在联赛中29轮积48分，排在第6位。\n主队各项赛事近6场4胜2负，状态不错;近5个主场全胜，主场状态火热。客队各项赛事近6场5胜1负，状态上佳;近5个客场3胜2负，客场状态不错。\n综合来看，主队稍占优势。\n双方近几年双方只交锋过一次，加拉塔萨雷获胜;在加拉塔萨雷的主场，近几年双方只交锋过一次，加拉塔萨雷获胜。\n本场半全场分析\n双方上半场打平的可能性为40%\n主队近6场主场的上半场:\n领先4，打平1，落后1/6场有进球，3场有失球\n客队近6场客场的上半场:\n落后1，打平4，领先1/1场有失球，2场有进球",
            "home_rank": 0,
            "away_rank": 0,
            "home_id": 0,
            "away_id": 0,
            "id": 8,
            "date": "2026-03-09",
            "home_stats": {
                "played": 26,
                "wins": 10,
                "draws": 7,
                "losses": 9,
                "goals_for": 35,
                "goals_against": 16,
                "avg_goals_for": "1.37",
                "avg_goals_against": "0.63",
                "clean_sheets": 6,
                "form": "WDLDW",
                "rank": 8
            },
            "away_stats": {
                "played": 24,
                "wins": 5,
                "draws": 4,
                "losses": 15,
                "goals_for": 17,
                "goals_against": 28,
                "avg_goals_for": "0.73",
                "avg_goals_against": "1.17",
                "clean_sheets": 6,
                "form": "LDWLL",
                "rank": 14
            },
            "h2h": [],
            "prediction": {
                "predicted_score": "1-0",
                "home_win_pct": 43.2,
                "draw_pct": 30.9,
                "away_win_pct": 25.9,
                "confidence": 76,
                "result": "主胜",
                "over_under_2_5": "小",
                "both_score": "否",
                "risk_level": "低",
                "gpt_analysis": "加拉塔萨主场面与土超状态都更强，近5个主场全胜，主场气势明显；利物浦近期整体战绩也不差，但欧战作客土耳其历来吃亏，且题面已指出近两次作客加拉塔萨均失利。伤停方面，主队缺员人数不少，但更多是轮换与边缘位置受损，整体框架影响相对可控；客队则有远藤航、布拉德利、巴伊切蒂奇等伤缺，阵容厚度与中后场轮换受影响。盘口给到主让1，结合模型主胜50%、平局30.9%、客胜19.1%，市场明显更倾向主队不败甚至赢球。但从双方近期状态对比看，利物浦并非弱势到完全被压制，且其淘汰赛经验、整体抗压能力仍强，官方分析也强调其本场首要目标是守和。综合伤停、主场强势、历史交锋压力与盘口深度后，独立裁决认为主队优势存在，但让1偏深，利物浦更有机会守住平局，比赛节奏可能先谨慎后提速，半场平局概率较高。",
                "gemini_analysis": "未响应",
                "gpt_score": "1-1",
                "gemini_score": "?",
                "value_bets_summary": [
                    "主胜 EV+99.0%"
                ]
            },
            "is_recommended": true
        },
        {
            "home_team": "亚特兰大",
            "away_team": "拜仁",
            "league": "欧冠",
            "match_num": "周二007",
            "sp_home": 4.25,
            "sp_draw": 4.15,
            "sp_away": 1.53,
            "odds_movement": "主胜平稳，客胜平稳",
            "handicap_info": "让1",
            "intelligence": {
                "h_inj": "乔治·斯卡尔维尼 停赛 红牌停赛 艾德森 肌肉受伤 查尔斯·德凯特拉雷 受伤 膝关节损伤 贾科莫·拉斯帕多里 大腿受伤 ",
                "g_inj": "阿方索·戴维斯 受伤 受伤 伊藤洋辉 受伤 肌肉受伤 曼努埃尔·诺伊尔 受伤 小腿受伤 卡西亚诺·基亚拉 受伤 踝关节受伤 哈里·凯恩 小腿受伤 巴拉·萨波科·恩迪亚耶 停赛 轮休 ",
                "h_bad": "1.亚特兰大在上场联赛中主场2比2战平乌迪内斯，球队在近3场正式比赛中取得2平1负的战绩，至今未尝胜绩，整体状态显得较为平庸。此外在防守端亚特兰大的表现缺乏稳定性，近6场正式比赛连续出现丢球情况，总计失球达到10个，场均丢球数为1.67个，防线稳固性明显不足，这给球队的后续比赛带来了巨大隐患。 2.亚特兰大虽在附加赛次回合上演惊天逆转淘汰多特蒙德，士气高涨，但本轮欧冠八分之一决赛首回合他们将遭遇本赛季欧洲足坛状态最火热的顶级豪门拜仁慕尼黑。拜仁不仅整体统治力惊人，客场作战能力同样强悍。反观亚特兰大近期表现起伏较大，防守端存在隐患，面对拜仁豪华攻击线恐难招架。综合考虑双方实力差距与近期状态，亚特兰大本场主场作战恐怕难以守住优势，首回合落败风险较高。 ",
                "g_bad": "1.拜仁本赛季近10个客场比赛，在落后的情况下最终客场输球率达100%。 2.拜仁门将诺伊尔因左小腿轻微肌肉纤维撕裂，至少将缺席两场比赛。他在球队4比1战胜门兴的比赛中受伤，官方通报确认其无缘客场对阵亚特兰大的欧冠八分之一决赛首回合。此外，后防大将戴维斯与轮换后卫伊藤洋辉虽已恢复训练，但复出前景尚不明朗，两人本场出战均成疑，这让拜仁防线面临严峻考验。 3.拜仁慕尼黑近期表现堪称攻防俱佳，在近8场正式比赛中合计打进24球，场均进球数高达3球，进攻端展现出稳定且高效的特质。防守方面球队在8场比赛里总计失球9个，场均丢球数为1.13个，期间更有2场成功零封对手，整体防守效率保持在尚可的水准，攻守两端的均衡发挥是球队近期战绩出色的关键所在。 ",
                "match_points": ""
            },
            "expert_intro": "拜仁慕尼黑联赛阶段8场取胜7场，攻入22球的攻击力令人闻风丧胆，加上哈利.卡尼8个入球以及米高.奥利斯6次助攻都是神射手和助攻王的有力竞争者，其中哈利.卡尼近3次欧冠联面对意甲对手攻入3球，拜仁慕尼黑今仗挥军有力先拔头筹。",
            "base_face": "主队是意甲的球队，目前在联赛中28轮积46分，排在第7位。客队是德甲的球队，目前在联赛中25轮积66分，排在第1位，状态火热。\n主队各项赛事近6场2胜2平2负，状态一般;近5个主场4胜1平，主场状态上佳。客队各项赛事近6场全胜，状态火热;近5个客场4胜1平，客场状态上佳。\n综合来看，客队优势较大。\n本场半全场分析\n主队上半场落后的可能性为35%\n主队近6场主场的上半场:\n领先4，打平0，落后2/4场有进球，2场有失球\n客队近6场客场的上半场:\n落后2，打平3，领先1/4场有失球，3场有进球",
            "home_rank": 0,
            "away_rank": 0,
            "home_id": 0,
            "away_id": 0,
            "id": 9,
            "date": "2026-03-09",
            "home_stats": {
                "played": 25,
                "wins": 8,
                "draws": 6,
                "losses": 11,
                "goals_for": 26,
                "goals_against": 22,
                "avg_goals_for": "1.05",
                "avg_goals_against": "0.9",
                "clean_sheets": 6,
                "form": "WWDLW",
                "rank": 11
            },
            "away_stats": {
                "played": 25,
                "wins": 8,
                "draws": 6,
                "losses": 11,
                "goals_for": 26,
                "goals_against": 22,
                "avg_goals_for": "1.05",
                "avg_goals_against": "0.9",
                "clean_sheets": 6,
                "form": "LLLLW",
                "rank": 11
            },
            "h2h": [],
            "prediction": {
                "predicted_score": "0-0",
                "home_win_pct": 37.0,
                "draw_pct": 32.6,
                "away_win_pct": 30.4,
                "confidence": 66,
                "result": "平局",
                "over_under_2_5": "小",
                "both_score": "否",
                "risk_level": "中",
                "gpt_analysis": "从基本面看，拜仁整体实力、近期战绩和进攻数据都占优，但本场伤停对其核心框架影响不小，尤其是诺伊尔、戴维斯以及凯恩的伤缺会明显削弱后场稳定性和前场终结力。亚特兰大方面同样有减员，斯卡尔维尼停赛、艾德森和德凯特拉雷受伤会影响中后场硬度与前场串联，但其主场近5战4胜1平，主场韧性较强。盘口给到让1，说明市场初始对拜仁仍有较高定位，不过结合伤停名单来看，这个让步对客队支撑略显偏深，与模型胜率中主队39.6%、平局32.6%、客队27.8%的分布存在明显背离，存在客队热度偏高的风险。半场数据层面，亚特兰大主场上半场主动性不差，而拜仁客场上半场领先率并不突出，因此客队想早早拉开差距的难度较大。综合判断，本场更适合逆市场热度，支持亚特兰大至少守住不败，比分倾向1比1，若主队把握反击效率更高，也有2比1取胜可能。",
                "gemini_analysis": "未响应",
                "gpt_score": "主队不败，首选平局，次选主胜",
                "gemini_score": "?",
                "value_bets_summary": [
                    "主胜 EV+68.3%"
                ]
            },
            "is_recommended": false
        },
        {
            "home_team": "马竞",
            "away_team": "热刺",
            "league": "欧冠",
            "match_num": "周二008",
            "sp_home": 1.45,
            "sp_draw": 4.05,
            "sp_away": 5.2,
            "odds_movement": "主胜平稳，客胜平稳",
            "handicap_info": "让-1",
            "intelligence": {
                "h_inj": "巴勃罗·巴里奥斯·里瓦斯 肌肉受伤 罗德里戈·门多萨 受伤 受伤 ",
                "g_inj": "詹姆斯·麦迪逊 受伤 膝关节损伤 伊夫·比苏马 停赛 轮休 德扬·库卢塞夫斯基 受伤 膝关节损伤 本·戴维斯 受伤 踝关节受伤 德斯蒂尼·乌多吉 受伤 肌肉受伤 威尔逊·奥多贝尔 受伤 膝关节损伤 卢卡斯·贝里瓦尔 受伤 踝关节受伤 穆罕默德·库杜斯 受伤 肌肉受伤 杰德·斯宾塞 小腿受伤 罗德里戈·本坦库尔 受伤 肌肉受伤 ",
                "h_bad": "1.马竞中场门多萨踝关节受伤，将缺席至4月底。门多萨冬窗加盟马竞以来各项赛事出场5次其中4场首发，他的缺席对球队的中场梳理和拦截有不小的影响。 2.马德里竞技近期防守端明显疲软，近6场正式比赛仅有1场完成零封，其余5场均告失球，合计丢掉11球，场均失球高达1.83粒。防线注意力不集中、协防衔接不畅等问题频发，需在攻守平衡上做出调整。 ",
                "g_bad": "1.热刺近期状态持续低迷，上轮联赛主场1-3负于水晶宫，惨遭联赛五连败，士气严重受挫。球队目前仅积29分，排名英超第16位，距离降级区仅有1分之隔，保级形势已岌岌可危。 2.热刺目前状态堪忧，仅以1分优势暂列降级区之上，保级压力空前巨大。本场欧冠客场作战结束仅4天，球队便将迎来一场关乎保级命运的关键战役，客场挑战英超卫冕冠军利物浦。在如此严峻的联赛形势下，热刺能否在欧冠中全力以赴令人存疑，其战意无疑要被打上折扣。 3.热刺主力边锋库杜斯肌肉损伤，将缺席至4月中旬。本赛季库杜斯各项赛事出场26次其中23场首发，打入3球并有5次助攻，他的缺席对球队的边路突破和进攻影响很大。轮换前锋奥多贝尔十字韧带撕裂，赛季报销。主力中场本坦库尔腿筋受伤，将缺席至4月中旬。中场核心麦迪逊十字韧带断裂，赛季报销。主力中场库卢膝关节受伤，将继续缺席。中场小将贝里瓦尔踝关节受伤，将缺席至4月底。后防老将本·戴维斯踝关节受伤，将缺席至4月中旬。主力边后卫斯宾塞小腿受伤，本场比赛出战成疑。另一边后卫乌多吉肌肉受伤，将继续缺席。 ",
                "match_points": ""
            },
            "expert_intro": "马德里体育会近4次面对英超对手只得1和3负未尝胜绩，而热刺今季明显是放弃联赛主打欧冠联，以马德里体育会今届欧冠联场场有失球的防守表现来看，他们今铺主场沦陷在所难免。",
            "base_face": "主队是西甲的球队，目前在联赛中27轮积54分，排在第3位，状态出色。客队是英超的球队，目前在联赛中29轮积29分，排在第16位，状态不佳。\n主队各项赛事近6场4胜1平1负，近5个主场4胜1负，状态上佳。客队各项赛事近6场1平5负，状态低迷;近5个客场1胜1平3负，客场状态较差。\n综合来看，主队优势较大。\n本场半全场分析\n主队上半场领先的可能性为43%\n主队近6场主场的上半场:\n领先1，打平4，落后1/5场有进球，5场有失球\n客队近6场客场的上半场:\n落后3，打平3，领先0/4场有失球，2场有进球",
            "home_rank": 0,
            "away_rank": 0,
            "home_id": 0,
            "away_id": 0,
            "id": 10,
            "date": "2026-03-09",
            "home_stats": {
                "played": 23,
                "wins": 8,
                "draws": 6,
                "losses": 9,
                "goals_for": 26,
                "goals_against": 18,
                "avg_goals_for": "1.16",
                "avg_goals_against": "0.81",
                "clean_sheets": 5,
                "form": "WLDDL",
                "rank": 10
            },
            "away_stats": {
                "played": 27,
                "wins": 7,
                "draws": 7,
                "losses": 13,
                "goals_for": 22,
                "goals_against": 29,
                "avg_goals_for": "0.84",
                "avg_goals_against": "1.08",
                "clean_sheets": 6,
                "form": "WWLDL",
                "rank": 13
            },
            "h2h": [],
            "prediction": {
                "predicted_score": "1-0",
                "home_win_pct": 40.7,
                "draw_pct": 31.8,
                "away_win_pct": 27.5,
                "confidence": 71,
                "result": "平局",
                "over_under_2_5": "小",
                "both_score": "否",
                "risk_level": "低",
                "gpt_analysis": "综合研判倾向于马竞不败，但让-1盘口下主队穿盘难度偏大，独立裁决更支持马竞小胜或平局。马竞联赛排名、近期战绩和主场表现明显占优，热刺联赛状态很差，且伤停名单更长，麦迪逊、库卢、乌多吉、本坦库尔等缺阵对中前场推进与边路覆盖影响较大，这会削弱其持续对攻能力。另一方面，马竞自身并非无隐患：欧冠连续失球反映防线稳定性一般，且专家观点提到其近年对英超球队战绩不佳，这与官方研报的主强客弱形成明显分歧。盘口仅开到马竞让-1，结合模型胜率主胜45.8%、平31.8%、客胜22.4%，说明市场对马竞大胜信心有限，更多是优势方定位而非碾压格局。半场数据上，马竞主场上半场领先率不高，热刺客场上半场虽然偏被动，但平局占比也不低，因此比赛更可能呈现马竞控场但效率一般、热刺残阵下以反击或定位球争取进球的走势。伤停层面客队减员更重，确实压低了爆冷概率，但不足以强支撑马竞净胜2球以上。独立判断：主胜方向略优，首选平局防范，盘口建议热刺+1更稳，比分倾向1-1，其次2-1。",
                "gemini_analysis": "未响应",
                "gpt_score": "马竞 1.39 - 1.08 热刺",
                "gemini_score": "?",
                "value_bets_summary": []
            },
            "is_recommended": false
        },
        {
            "home_team": "纽卡斯尔",
            "away_team": "巴萨",
            "league": "欧冠",
            "match_num": "周二009",
            "sp_home": 2.64,
            "sp_draw": 3.7,
            "sp_away": 2.08,
            "odds_movement": "主胜升水，客胜降水",
            "handicap_info": "让1",
            "intelligence": {
                "h_inj": "马克·吉莱斯皮 停赛 轮休 法比安·舍尔 受伤 踝关节扭伤 刘易斯·麦利 受伤 膝关节受伤 布鲁诺·吉马良斯 受伤 肌肉挫伤 埃米尔·克拉夫特 受伤 膝关节受伤 ",
                "g_inj": "加维 受伤 膝关节受伤 亚历杭德罗·巴尔德 受伤 腿筋受伤 弗兰基·德容 受伤 腿筋受伤 克里斯滕森 受伤 膝关节受伤 朱尔·孔德 受伤 腿筋受伤 ",
                "h_bad": "1.纽卡斯尔联近期状态起伏较大，上场足总杯主场1-3不敌曼城，惨遭淘汰，士气受到一定打击。近6场正式比赛取得3胜3负，胜负交替，缺乏稳定性。 2.纽卡斯尔联近期防守问题十分突出，近10场正式比赛场场失球，无一零封，合计丢掉20球，场均失球高达2粒。防线组织松散、盯人不紧，面对中下游球队也频频被破门，暴露出后防体系的严重漏洞。 3.纽卡斯尔联中场小将麦利膝关节受伤，将缺席至4月中旬。本赛季欧冠麦利出场7次其中2场首发，打入1球。替补后卫克拉夫特膝关节损伤，将继续缺席。后防老将舍尔踝关节受伤，将缺席至4月中旬。舍尔本赛季欧冠出场3次其中2场首发。此外，中场核心吉马良斯肌肉损伤，将缺席至4月中旬。本赛季欧冠吉马良斯出场7次全部首发。他的缺席对球队的中场组织调度和中场拦截影响巨大。 4.纽卡斯尔联在欧冠历史上与巴塞罗那交手3次，全部告负，处于明显下风。双方最近一次碰面是在本赛季欧冠联赛阶段，纽卡斯尔联主场1-2不敌巴萨，延续了此前的劣势。 ",
                "g_bad": "1.近日，巴萨传奇哈维接受媒体采访时炮轰俱乐部现任主席拉波尔塔，他表示：我无意重返巴萨，也无意像传闻那样加入丰特的团队。不，我对任何事都没兴趣。我想我现在是永远不会再回巴萨了，永远。我结束了我（在巴萨）的球员生涯和教练生涯，我帮助了他们，我认为那是一段非常积极的时期，我认为我们在足球层面上拯救了球队和俱乐部。从现在开始，我只对说真话感兴趣。梅西不回巴萨，是因为拉波尔塔不想要他回来，不是因为西甲联赛，也不是因为豪尔赫·梅西要更多的钱，这些都是谎言。是拉波尔塔以及他的团队说不行，说他负担不起，说他掌握着绝对的权力，而梅西会滥用这种权力。换句话说，将会爆发战争。这是他跟我说的，原话如此。目前，巴塞罗那正处在俱乐部主席大选的关键阶段，各派势力明争暗斗、角力不断，场外的博弈与舆论风波极有可能对更衣室氛围和球员心态造成干扰，为球队的竞技表现增添不确定因素。 ",
                "match_points": ""
            },
            "expert_intro": "联赛阶段双方就有过交锋，巴塞隆拿最终作客赢球，欧战经验纽卡素明显输蚀，多线作战班底深度略显不足，当然看好巴塞隆拿是役挥军奏捷而回。",
            "base_face": "主队是英超的球队，目前在联赛中29轮积39分，排在第12位。客队是西甲的球队，目前在联赛中27轮积67分，排在第1位，状态火热。\n主队各项赛事近6场3胜3负，近5个主场2胜3负，状态一般。客队各项赛事近6场4胜2负，近5个客场3胜2负，状态不错。\n综合来看，客队稍占优势。\n双方近几年双方只交锋过一次，巴塞罗那获胜;在纽卡斯尔的主场，近几年双方只交锋过一次，巴塞罗那获胜。\n本场半全场分析\n双方上半场打平的可能性为45%\n主队近6场主场的上半场:\n领先1，打平2，落后3/5场有进球，5场有失球\n客队近6场客场的上半场:\n落后1，打平3，领先2/3场有失球，3场有进球",
            "home_rank": 0,
            "away_rank": 0,
            "home_id": 0,
            "away_id": 0,
            "id": 11,
            "date": "2026-03-09",
            "home_stats": {
                "played": 27,
                "wins": 7,
                "draws": 7,
                "losses": 13,
                "goals_for": 22,
                "goals_against": 29,
                "avg_goals_for": "0.84",
                "avg_goals_against": "1.08",
                "clean_sheets": 6,
                "form": "WLWDL",
                "rank": 13
            },
            "away_stats": {
                "played": 28,
                "wins": 8,
                "draws": 7,
                "losses": 13,
                "goals_for": 26,
                "goals_against": 27,
                "avg_goals_for": "0.94",
                "avg_goals_against": "0.99",
                "clean_sheets": 7,
                "form": "WDLWL",
                "rank": 12
            },
            "h2h": [],
            "prediction": {
                "predicted_score": "0-0",
                "home_win_pct": 35.0,
                "draw_pct": 36.8,
                "away_win_pct": 28.2,
                "confidence": 46,
                "result": "平局",
                "over_under_2_5": "小",
                "both_score": "否",
                "risk_level": "高",
                "gpt_analysis": "独立裁决偏向巴萨客胜。理由：1）基本面上，巴萨联赛统治力、欧战经验、近期整体状态均优于纽卡斯尔；2）纽卡斯尔伤停更伤筋动骨，法比安·舍尔与布鲁诺·吉马良斯的缺阵对中后场稳定性和攻防转换影响较大，阵容厚度本就一般，多线作战下隐患更明显；3）巴萨同样有伤停，德容、孔德、巴尔德缺席会削弱中后场控制和边路质量，但其替代资源仍优于主队；4）盘口为客让1，且主胜升水、客胜降水，资金流向与机构态度更支持客队方向，和专家分析一致；5）官方模型给出客胜仅26.9%，与让1盘口明显不匹配，存在低估客队硬实力与市场预期的嫌疑。综合伤停影响、实力差、欧战属性与盘口变化，本场更合理结论是巴萨小胜，防平但不看主胜。",
                "gemini_analysis": "未响应",
                "gpt_score": {
                    "home_win": 24,
                    "draw": 27,
                    "away_win": 49
                },
                "gemini_score": "?",
                "value_bets_summary": []
            },
            "is_recommended": false
        }
    ],
    "top4_ids": [
        3,
        4,
        8
    ]
}